pyelegantsdds/__init__.py
pyelegantsdds/elegant_command.py
pyelegantsdds/elegantrun.py
pyelegantsdds/sdds.py
pyelegantsdds/tools/__init__.py
pyelegantsdds/tools/sddsutils.py
pyelegantsdds-0.2.0.dist-info/entry_points.txt
pyelegantsdds-0.2.0.dist-info/LICENSE
pyelegantsdds-0.2.0.dist-info/WHEEL
pyelegantsdds-0.2.0.dist-info/METADATA
pyelegantsdds-0.2.0.dist-info/RECORD
